Flask_AtlassianConnect-0.0.1.dist-info/DESCRIPTION.rst
Flask_AtlassianConnect-0.0.1.dist-info/METADATA
Flask_AtlassianConnect-0.0.1.dist-info/RECORD
Flask_AtlassianConnect-0.0.1.dist-info/WHEEL
Flask_AtlassianConnect-0.0.1.dist-info/metadata.json
Flask_AtlassianConnect-0.0.1.dist-info/top_level.txt
flask_atlassian_connect/__init__.py
flask_atlassian_connect/base.py
flask_atlassian_connect/client.py
flask_atlassian_connect/tests/__init__.py
flask_atlassian_connect/tests/test_addon.py
