Metadata-Version: 2.0
Name: Flask-AtlassianConnect
Version: 0.0.1
Summary: Atlassian Connect Helper
Home-page: https://github.com/halkeye/flask_atlassian_connect
Author: Gavin Mogan
Author-email: opensource@gavinmogan.com
License: Apache License
Requires-Dist: Flask (>=0.12.2)
Requires-Dist: requests (>=2.4.3)
Requires-Dist: PyJWT (>=1.4.2)
Requires-Dist: atlassian-jwt (>=1.8.1)
